<?xml version="1.0" encoding="UTF-8" standalone="yes"?>
<dict>
    <entry key="blockstrategy">
        <dict>
            <entry key="name">
                <string>net.postchain.base.BaseBlockBuildingStrategy</string>
            </entry>
            <entry key="maxblocktime">
                <int>15000</int>
            </entry>
            <entry key="blockdelay">
                <int>750</int>
            </entry>
            <entry key="maxblocktransactions">
                <int>500</int>
            </entry>
        </dict>
    </entry>
    <entry key="configurationfactory">
        <string>net.postchain.gtx.GTXBlockchainConfigurationFactory</string>
    </entry>
    <entry key="signers">
        <array>
            <bytea>0350fe40766bc0ce8d08b3f5b810e49a8352fdd458606bd5fafe5acdcdc8ff3f57</bytea>
        </array>
    </entry>
    <entry key="gtx">
        <dict>
            <entry key="modules">
                <array>
                    <string>net.postchain.rell.module.RellPostchainModuleFactory</string>
                    <string>net.postchain.gtx.StandardOpsGTXModule</string>
                </array>
            </entry>
            <entry key="rell">
                <dict>
                    <entry key="moduleName">
                        <string>chrotonomy</string>
                    </entry>
                    <entry key="mainFile">
                        <string>main.rell</string>
                    </entry>
                    <entry key="files_v0.8">
                        <dict>
                            <entry key="main.rell">
                                <string>module/main.rell</string>
                            </entry>
                            <entry key="util/index.rell">
                                <string>module/util/index.rell</string>
                            </entry>
                            <entry key="util/text-util.rell">
                                <string>module/util/text-util.rell</string>
                            </entry>

                            <entry key="user/index.rell">
                                <string>module/user/index.rell</string>
                            </entry>
                            <entry key="user/operations.rell">
                                <string>module/user/operations.rell</string>
                            </entry>
                            <entry key="user/queries.rell">
                                <string>module/user/queries.rell</string>
                            </entry>

                            <entry key="user/settings/index.rell">
                                <string>module/user/settings/index.rell</string>
                            </entry>
                            <entry key="user/settings/operations.rell">
                                <string>module/user/settings/operations.rell</string>
                            </entry>
                            <entry key="user/settings/queries.rell">
                                <string>module/user/settings/queries.rell</string>
                            </entry>

                            <entry key="user/meta/index.rell">
                                <string>module/user/meta/index.rell</string>
                            </entry>
                            <entry key="user/meta/operations.rell">
                                <string>module/user/meta/operations.rell</string>
                            </entry>
                            <entry key="user/meta/queries.rell">
                                <string>module/user/meta/queries.rell</string>
                            </entry>

                            <entry key="topic/index.rell">
                                <string>module/topic/index.rell</string>
                            </entry>
                            <entry key="topic/operations.rell">
                                <string>module/topic/operations.rell</string>
                            </entry>
                            <entry key="topic/queries.rell">
                                <string>module/topic/queries.rell</string>
                            </entry>

                            <entry key="topic/rating/index.rell">
                                <string>module/topic/rating/index.rell</string>
                            </entry>
                            <entry key="topic/rating/operations.rell">
                                <string>module/topic/rating/operations.rell</string>
                            </entry>
                            <entry key="topic/rating/queries.rell">
                                <string>module/topic/rating/queries.rell</string>
                            </entry>

                            <entry key="topic/subscription/index.rell">
                                <string>module/topic/subscription/index.rell</string>
                            </entry>
                            <entry key="topic/subscription/operations.rell">
                                <string>module/topic/subscription/operations.rell</string>
                            </entry>
                            <entry key="topic/subscription/queries.rell">
                                <string>module/topic/subscription/queries.rell</string>
                            </entry>

                            <entry key="notifications/index.rell">
                                <string>module/notifications/index.rell</string>
                            </entry>
                            <entry key="notifications/operations.rell">
                                <string>module/notifications/operations.rell</string>
                            </entry>
                            <entry key="notifications/queries.rell">
                                <string>module/notifications/queries.rell</string>
                            </entry>

                            <entry key="channel/index.rell">
                                <string>module/channel/index.rell</string>
                            </entry>
                            <entry key="channel/operations.rell">
                                <string>module/channel/operations.rell</string>
                            </entry>
                            <entry key="channel/queries.rell">
                                <string>module/channel/queries.rell</string>
                            </entry>

                            <entry key="follow/index.rell">
                                <string>module/follow/index.rell</string>
                            </entry>
                            <entry key="follow/operations.rell">
                                <string>module/follow/operations.rell</string>
                            </entry>
                            <entry key="follow/queries.rell">
                                <string>module/follow/queries.rell</string>
                            </entry>

                            <entry key="election/index.rell">
                                <string>module/election/index.rell</string>
                            </entry>
                            <entry key="election/operations.rell">
                                <string>module/election/operations.rell</string>
                            </entry>
                            <entry key="election/queries.rell">
                                <string>module/election/queries.rell</string>
                            </entry>

                            <entry key="representative/index.rell">
                                <string>module/representative/index.rell</string>
                            </entry>
                            <entry key="representative/operations.rell">
                                <string>module/representative/operations.rell</string>
                            </entry>
                            <entry key="representative/queries.rell">
                                <string>module/representative/queries.rell</string>
                            </entry>

                            <entry key="representative/report/index.rell">
                                <string>module/representative/report/index.rell</string>
                            </entry>
                            <entry key="representative/report/operations.rell">
                                <string>module/representative/report/operations.rell</string>
                            </entry>
                            <entry key="representative/report/queries.rell">
                                <string>module/representative/report/queries.rell</string>
                            </entry>
                        </dict>
                    </entry>
                </dict>
            </entry>
        </dict>
    </entry>
</dict>
